COPYING
MANIFEST.in
README.rst
openscad_dxf.inx
setup.py
inkscape_openscad_dxf.egg-info/PKG-INFO
inkscape_openscad_dxf.egg-info/SOURCES.txt
inkscape_openscad_dxf.egg-info/dependency_links.txt
inkscape_openscad_dxf.egg-info/pbr.json
inkscape_openscad_dxf.egg-info/requires.txt
inkscape_openscad_dxf.egg-info/top_level.txt
openscad_dxf/__init__.py
openscad_dxf/dxf_color.py
openscad_dxf/inkinkex.py
openscad_dxf/inkutils.py
openscad_dxf/object2path.py
openscad_dxf/openscad_dxf.py