Metadata-Version: 1.1
Name: inkscape-openscad-dxf
Version: 0.0.2
Summary: Inkscape OpenSCAD DXF Export
Home-page: https://github.com/brad/Inkscape-OpenSCAD-DXF-Export
Author: Brad Pitcher
Author-email: bradpitcher@gmail.com
License: GPL
Platform: UNKNOWN
Classifier: Intended Audience :: Developers
Classifier: Natural Language :: English
Classifier: License :: OSI Approved :: GNU General Public License v2 or later (GPLv2+)
Classifier: Programming Language :: Python :: 2.7
Classifier: Programming Language :: Python :: Implementation :: PyPy
